<?xml version="1.0" encoding="UTF-8"?>
<!DOCTYPE suite SYSTEM "http://testng.org/testng-1.0.dtd">

<suite name="TestNGListenerSuite">
	<listeners>
		<listener class-name="LoginPage.Listeners"></listener>
		<listener class-name="ProductsPage.Listeners"></listener>
	</listeners>
	
	<test name="SwagLabs">
		<classes>
			<class name="LoginPage.TS_LOGIN_PAGE_01">
				<methods>
					<include name="TC_LP_00"/>
					<include name="TC_LP_01"/>
					<include name="TC_LP_02"/>
					<include name="TC_LP_03"/>
					<include name="TC_LP_04"/>
					<include name="TC_LP_05"/>
					<include name="TC_LP_06"/>
					<include name="TC_LP_07"/>
					<include name="TC_LP_08"/>
					<include name="TC_LP_09"/>
					<include name="TC_LP_10"/>
					<include name="TC_LP_11"/>
					<include name="TC_LP_12"/>
				</methods>
			</class>
			<class name="LoginPage.TS_LOGIN_FUNCTIONALITY_02">
				<methods>
					<include name="TC_LF_00"/>
					<include name="TC_LF_01"/>
					<include name="TC_LF_02"/>
					<include name="TC_LF_03"/>
					<include name="TC_LF_04"/>
					<include name="TC_LF_05"/>
					<include name="TC_LF_06"/>
					<include name="TC_LF_07"/>
					<include name="TC_LF_08"/>
					<include name="TC_LF_09"/>
					<include name="TC_LF_10"/>
					<include name="TC_LF_11"/>
				</methods>
			</class>
			<class name="ProductsPage.TS_PRODUCTS_PAGE_01">
				<methods>
					<include name="TC_PP_00"></include>
					<include name="TC_PP_01"></include>
				</methods>
			</class>
			<class name="ProductsPage.TS_HEADER_02">
				<methods>
					<include name="TC_H_00"></include>
					<include name="TC_H_01"></include>
					<include name="TC_H_02"></include>
					<include name="TC_H_03"></include>
					
					
					
					
				</methods>
			</class>
		</classes>
	</test>
</suite>